[{"id":1213150001,"province_id":12,"regency_id":1213,"district_id":1213150,"value":"PAYA BENGKUANG"},{"id":1213150002,"province_id":12,"regency_id":1213,"district_id":1213150,"value":"AIR HITAM"},{"id":1213150003,"province_id":12,"regency_id":1213,"district_id":1213150,"value":"PADANG LANGKAT"},{"id":1213150004,"province_id":12,"regency_id":1213,"district_id":1213150,"value":"PALUH MANIS"},{"id":1213150005,"province_id":12,"regency_id":1213,"district_id":1213150,"value":"PEKAN GEBANG"},{"id":1213150006,"province_id":12,"regency_id":1213,"district_id":1213150,"value":"DOGANG"},{"id":1213150007,"province_id":12,"regency_id":1213,"district_id":1213150,"value":"SANGGA LIMA PERKEBUNAN SERAPUH"},{"id":1213150008,"province_id":12,"regency_id":1213,"district_id":1213150,"value":"PASAR RAWA"},{"id":1213150009,"province_id":12,"regency_id":1213,"district_id":1213150,"value":"KWALA GEBANG"},{"id":1213150010,"province_id":12,"regency_id":1213,"district_id":1213150,"value":"BUKIT MENGKIRAI"},{"id":1213150011,"province_id":12,"regency_id":1213,"district_id":1213150,"value":"PASIRAN"}]