[{"id":1904020006,"province_id":19,"regency_id":1904,"district_id":1904020,"value":"TANJUNG GUNUNG"},{"id":1904020008,"province_id":19,"regency_id":1904,"district_id":1904020,"value":"AIRMESU"},{"id":1904020010,"province_id":19,"regency_id":1904,"district_id":1904020,"value":"MANGKOL"},{"id":1904020012,"province_id":19,"regency_id":1904,"district_id":1904020,"value":"PADANG BARU"},{"id":1904020015,"province_id":19,"regency_id":1904,"district_id":1904020,"value":"BATU BELUBANG"},{"id":1904020016,"province_id":19,"regency_id":1904,"district_id":1904020,"value":"PEDINDANG"},{"id":1904020017,"province_id":19,"regency_id":1904,"district_id":1904020,"value":"AIRMESU TIMUR"},{"id":1904020018,"province_id":19,"regency_id":1904,"district_id":1904020,"value":"KEBINTIK"}]