[{"id":8207020001,"province_id":82,"regency_id":8207,"district_id":8207020,"value":"SAMBIKI"},{"id":8207020002,"province_id":82,"regency_id":8207,"district_id":8207020,"value":"SAMBIKI BARU"},{"id":8207020003,"province_id":82,"regency_id":8207,"district_id":8207020,"value":"SANGOWO"},{"id":8207020004,"province_id":82,"regency_id":8207,"district_id":8207020,"value":"MIRA"},{"id":8207020005,"province_id":82,"regency_id":8207,"district_id":8207020,"value":"RAHMAT"},{"id":8207020006,"province_id":82,"regency_id":8207,"district_id":8207020,"value":"WEWEMO"},{"id":8207020007,"province_id":82,"regency_id":8207,"district_id":8207020,"value":"BUHO BUHO"},{"id":8207020008,"province_id":82,"regency_id":8207,"district_id":8207020,"value":"LIFAO"},{"id":8207020009,"province_id":82,"regency_id":8207,"district_id":8207020,"value":"GAMLAMO"},{"id":8207020010,"province_id":82,"regency_id":8207,"district_id":8207020,"value":"SANGOWO BARAT"},{"id":8207020011,"province_id":82,"regency_id":8207,"district_id":8207020,"value":"SANGOWO TIMUR"},{"id":8207020012,"province_id":82,"regency_id":8207,"district_id":8207020,"value":"DOKU MIRA"},{"id":8207020013,"province_id":82,"regency_id":8207,"district_id":8207020,"value":"GOSOMA MALUKU"},{"id":8207020014,"province_id":82,"regency_id":8207,"district_id":8207020,"value":"HINO"},{"id":8207020015,"province_id":82,"regency_id":8207,"district_id":8207020,"value":"SESELI JAYA"}]