[{"id":3204250001,"province_id":32,"regency_id":3204,"district_id":3204250,"value":"NANJUNG"},{"id":3204250002,"province_id":32,"regency_id":3204,"district_id":3204250,"value":"MEKAR RAHAYU"},{"id":3204250003,"province_id":32,"regency_id":3204,"district_id":3204250,"value":"RAHAYU"},{"id":3204250004,"province_id":32,"regency_id":3204,"district_id":3204250,"value":"CIGONDEWAH HILIR"},{"id":3204250005,"province_id":32,"regency_id":3204,"district_id":3204250,"value":"MARGAASIH"},{"id":3204250006,"province_id":32,"regency_id":3204,"district_id":3204250,"value":"LAGADAR"}]