[{"id":6106090001,"province_id":61,"regency_id":6106,"district_id":6106090,"value":"SUNGAI KELIK"},{"id":6106090002,"province_id":61,"regency_id":6106,"district_id":6106090,"value":"LEMBAH HIJAU II"},{"id":6106090003,"province_id":61,"regency_id":6106,"district_id":6106090,"value":"LEMBAH HIJAU I"},{"id":6106090004,"province_id":61,"regency_id":6106,"district_id":6106090,"value":"NANGA TAYAP"},{"id":6106090005,"province_id":61,"regency_id":6106,"district_id":6106090,"value":"SIANTAU RAYA"},{"id":6106090006,"province_id":61,"regency_id":6106,"district_id":6106090,"value":"BATUMAS"},{"id":6106090008,"province_id":61,"regency_id":6106,"district_id":6106090,"value":"PANGKALAN SUKA"},{"id":6106090009,"province_id":61,"regency_id":6106,"district_id":6106090,"value":"PANGKALAN TELOK"},{"id":6106090010,"province_id":61,"regency_id":6106,"district_id":6106090,"value":"SEBADAK RAYA"},{"id":6106090011,"province_id":61,"regency_id":6106,"district_id":6106090,"value":"SIMPANG TIGA SEMBELANGAAN"},{"id":6106090012,"province_id":61,"regency_id":6106,"district_id":6106090,"value":"MENSUBANG"},{"id":6106090013,"province_id":61,"regency_id":6106,"district_id":6106090,"value":"TAJOK KAYONG"},{"id":6106090014,"province_id":61,"regency_id":6106,"district_id":6106090,"value":"KAYONG UTARA"},{"id":6106090015,"province_id":61,"regency_id":6106,"district_id":6106090,"value":"KAYONG HULU"},{"id":6106090016,"province_id":61,"regency_id":6106,"district_id":6106090,"value":"SEPAKAT JAYA"},{"id":6106090017,"province_id":61,"regency_id":6106,"district_id":6106090,"value":"CEGOLAK"},{"id":6106090018,"province_id":61,"regency_id":6106,"district_id":6106090,"value":"PATEH BENTENG"},{"id":6106090019,"province_id":61,"regency_id":6106,"district_id":6106090,"value":"TANJUNG MEDAN"},{"id":6106090020,"province_id":61,"regency_id":6106,"district_id":6106090,"value":"KAYUNG TUHE"}]