[{"id":3312090001,"province_id":33,"regency_id":3312,"district_id":3312090,"value":"GLESUNGREJO"},{"id":3312090002,"province_id":33,"regency_id":3312,"district_id":3312090,"value":"GAMBIRANOM"},{"id":3312090003,"province_id":33,"regency_id":3312,"district_id":3312090,"value":"BALEPANJANG"},{"id":3312090004,"province_id":33,"regency_id":3312,"district_id":3312090,"value":"WATUAGUNG"},{"id":3312090005,"province_id":33,"regency_id":3312,"district_id":3312090,"value":"BATURETNO"},{"id":3312090006,"province_id":33,"regency_id":3312,"district_id":3312090,"value":"BELIKURIP"},{"id":3312090007,"province_id":33,"regency_id":3312,"district_id":3312090,"value":"TEMON"},{"id":3312090008,"province_id":33,"regency_id":3312,"district_id":3312090,"value":"SARADAN"},{"id":3312090009,"province_id":33,"regency_id":3312,"district_id":3312090,"value":"TALUNOMBO"},{"id":3312090010,"province_id":33,"regency_id":3312,"district_id":3312090,"value":"SENDANGREJO"},{"id":3312090011,"province_id":33,"regency_id":3312,"district_id":3312090,"value":"BOTO"},{"id":3312090012,"province_id":33,"regency_id":3312,"district_id":3312090,"value":"KEDUNGOMBO"},{"id":3312090013,"province_id":33,"regency_id":3312,"district_id":3312090,"value":"SETROREJO"}]