[{"id":1220020001,"province_id":12,"regency_id":1220,"district_id":1220020,"value":"AEK BARGOT"},{"id":1220020002,"province_id":12,"regency_id":1220,"district_id":1220020,"value":"PAMUNTARAN"},{"id":1220020003,"province_id":12,"regency_id":1220,"district_id":1220020,"value":"BALIMBING JULU"},{"id":1220020004,"province_id":12,"regency_id":1220,"district_id":1220020,"value":"BALIMBING JAE"},{"id":1220020005,"province_id":12,"regency_id":1220,"district_id":1220020,"value":"SOBAR"},{"id":1220020006,"province_id":12,"regency_id":1220,"district_id":1220020,"value":"SIPUPUS LOMBANG"},{"id":1220020007,"province_id":12,"regency_id":1220,"district_id":1220020,"value":"PADANG BUJUR"},{"id":1220020008,"province_id":12,"regency_id":1220,"district_id":1220020,"value":"PARAN GADUNG"},{"id":1220020009,"province_id":12,"regency_id":1220,"district_id":1220020,"value":"PADANG BARUAS"},{"id":1220020010,"province_id":12,"regency_id":1220,"district_id":1220020,"value":"UBAR"},{"id":1220020011,"province_id":12,"regency_id":1220,"district_id":1220020,"value":"BALAKKA"},{"id":1220020012,"province_id":12,"regency_id":1220,"district_id":1220020,"value":"GARIANG"},{"id":1220020013,"province_id":12,"regency_id":1220,"district_id":1220020,"value":"LANTOSAN II"},{"id":1220020014,"province_id":12,"regency_id":1220,"district_id":1220020,"value":"BATU GANA"},{"id":1220020015,"province_id":12,"regency_id":1220,"district_id":1220020,"value":"PARUPUK JAE"},{"id":1220020016,"province_id":12,"regency_id":1220,"district_id":1220020,"value":"PARUPUK JULU"},{"id":1220020017,"province_id":12,"regency_id":1220,"district_id":1220020,"value":"PANCUR PANGKO"},{"id":1220020018,"province_id":12,"regency_id":1220,"district_id":1220020,"value":"PARAN NANGKA"},{"id":1220020019,"province_id":12,"regency_id":1220,"district_id":1220020,"value":"HASAMBI"},{"id":1220020020,"province_id":12,"regency_id":1220,"district_id":1220020,"value":"SIALANG"},{"id":1220020021,"province_id":12,"regency_id":1220,"district_id":1220020,"value":"BATU RANCANG"},{"id":1220020022,"province_id":12,"regency_id":1220,"district_id":1220020,"value":"SIUNGGAM DOLOK"},{"id":1220020023,"province_id":12,"regency_id":1220,"district_id":1220020,"value":"SITANGGORU"}]