[{"id":3515030001,"province_id":35,"regency_id":3515,"district_id":3515030,"value":"TAMBAKREJO"},{"id":3515030004,"province_id":35,"regency_id":3515,"district_id":3515030,"value":"KEDUNGRAWAN"},{"id":3515030005,"province_id":35,"regency_id":3515,"district_id":3515030,"value":"TANJEG WAGIR"},{"id":3515030006,"province_id":35,"regency_id":3515,"district_id":3515030,"value":"MOJORUNTUT"},{"id":3515030007,"province_id":35,"regency_id":3515,"district_id":3515030,"value":"GADING"},{"id":3515030008,"province_id":35,"regency_id":3515,"district_id":3515030,"value":"WANGKAL"},{"id":3515030009,"province_id":35,"regency_id":3515,"district_id":3515030,"value":"JENGGOT"},{"id":3515030010,"province_id":35,"regency_id":3515,"district_id":3515030,"value":"WAUNG"},{"id":3515030011,"province_id":35,"regency_id":3515,"district_id":3515030,"value":"PLOSO"},{"id":3515030012,"province_id":35,"regency_id":3515,"district_id":3515030,"value":"REJENI"},{"id":3515030013,"province_id":35,"regency_id":3515,"district_id":3515030,"value":"KANDANGAN"},{"id":3515030016,"province_id":35,"regency_id":3515,"district_id":3515030,"value":"CANGKRING"},{"id":3515030018,"province_id":35,"regency_id":3515,"district_id":3515030,"value":"WONOMLATI"},{"id":3515030019,"province_id":35,"regency_id":3515,"district_id":3515030,"value":"BALONGGARUT"}]