[{"id":1273010,"province_id":12,"regency_id":1273,"value":"SIANTAR MARIHAT"},{"id":1273011,"province_id":12,"regency_id":1273,"value":"SIANTAR MARIMBUN"},{"id":1273020,"province_id":12,"regency_id":1273,"value":"SIANTAR SELATAN"},{"id":1273030,"province_id":12,"regency_id":1273,"value":"SIANTAR BARAT"},{"id":1273040,"province_id":12,"regency_id":1273,"value":"SIANTAR UTARA"},{"id":1273050,"province_id":12,"regency_id":1273,"value":"SIANTAR TIMUR"},{"id":1273060,"province_id":12,"regency_id":1273,"value":"SIANTAR MARTOBA"},{"id":1273061,"province_id":12,"regency_id":1273,"value":"SIANTAR SITALASARI"}]