[{"id":3318020001,"province_id":33,"regency_id":3318,"district_id":3318020,"value":"JIMBARAN"},{"id":3318020002,"province_id":33,"regency_id":3318,"district_id":3318020,"value":"DURENSAWIT"},{"id":3318020005,"province_id":33,"regency_id":3318,"district_id":3318020,"value":"PURWOKERTO"},{"id":3318020006,"province_id":33,"regency_id":3318,"district_id":3318020,"value":"SUMBERSARI"},{"id":3318020007,"province_id":33,"regency_id":3318,"district_id":3318020,"value":"BRATI"},{"id":3318020008,"province_id":33,"regency_id":3318,"district_id":3318020,"value":"JATIROTO"},{"id":3318020009,"province_id":33,"regency_id":3318,"district_id":3318020,"value":"KAYEN"},{"id":3318020010,"province_id":33,"regency_id":3318,"district_id":3318020,"value":"TRIMULYO"},{"id":3318020011,"province_id":33,"regency_id":3318,"district_id":3318020,"value":"SRIKATON"},{"id":3318020012,"province_id":33,"regency_id":3318,"district_id":3318020,"value":"PASURUHAN"},{"id":3318020013,"province_id":33,"regency_id":3318,"district_id":3318020,"value":"PESAGI"},{"id":3318020014,"province_id":33,"regency_id":3318,"district_id":3318020,"value":"ROGOMULYO"},{"id":3318020015,"province_id":33,"regency_id":3318,"district_id":3318020,"value":"TALUN"},{"id":3318020016,"province_id":33,"regency_id":3318,"district_id":3318020,"value":"BOLOAGUNG"},{"id":3318020017,"province_id":33,"regency_id":3318,"district_id":3318020,"value":"SUNDOLUHUR"}]