[{"id":6405050001,"province_id":64,"regency_id":6405,"district_id":6405050,"value":"LONG LANUK"},{"id":6405050002,"province_id":64,"regency_id":6405,"district_id":6405050,"value":"TUMBIT DAYAK"},{"id":6405050004,"province_id":64,"regency_id":6405,"district_id":6405050,"value":"INARAN"},{"id":6405050005,"province_id":64,"regency_id":6405,"district_id":6405050,"value":"PEGAT BUKUR"},{"id":6405050006,"province_id":64,"regency_id":6405,"district_id":6405050,"value":"RANTAU PANJANG"},{"id":6405050007,"province_id":64,"regency_id":6405,"district_id":6405050,"value":"SAMBALIUNG"},{"id":6405050008,"province_id":64,"regency_id":6405,"district_id":6405050,"value":"BEBANIR"},{"id":6405050009,"province_id":64,"regency_id":6405,"district_id":6405050,"value":"GURIMBANG"},{"id":6405050010,"province_id":64,"regency_id":6405,"district_id":6405050,"value":"TANJUNG PERANGAT"},{"id":6405050011,"province_id":64,"regency_id":6405,"district_id":6405050,"value":"SUKAN TENGAH"},{"id":6405050012,"province_id":64,"regency_id":6405,"district_id":6405050,"value":"SUARAN"},{"id":6405050013,"province_id":64,"regency_id":6405,"district_id":6405050,"value":"PESAYAN"},{"id":6405050014,"province_id":64,"regency_id":6405,"district_id":6405050,"value":"PILANJAU"},{"id":6405050015,"province_id":64,"regency_id":6405,"district_id":6405050,"value":"BENA BARU"}]