[{"id":1408012001,"province_id":14,"regency_id":1408,"district_id":1408012,"value":"BULUH MANIS"},{"id":1408012002,"province_id":14,"regency_id":1408,"district_id":1408012,"value":"PETANI"},{"id":1408012003,"province_id":14,"regency_id":1408,"district_id":1408012,"value":"TAMBUSAI BATANG DUI"},{"id":1408012004,"province_id":14,"regency_id":1408,"district_id":1408012,"value":"SIMPANG PADANG"},{"id":1408012005,"province_id":14,"regency_id":1408,"district_id":1408012,"value":"PEMATANG OBO"},{"id":1408012006,"province_id":14,"regency_id":1408,"district_id":1408012,"value":"BALAI MAKAM"},{"id":1408012007,"province_id":14,"regency_id":1408,"district_id":1408012,"value":"AIR KULIM"},{"id":1408012008,"province_id":14,"regency_id":1408,"district_id":1408012,"value":"BONCAH MAHANG"},{"id":1408012009,"province_id":14,"regency_id":1408,"district_id":1408012,"value":"SEBANGAR"},{"id":1408012010,"province_id":14,"regency_id":1408,"district_id":1408012,"value":"PAMESI"},{"id":1408012011,"province_id":14,"regency_id":1408,"district_id":1408012,"value":"BUMBUNG"},{"id":1408012012,"province_id":14,"regency_id":1408,"district_id":1408012,"value":"KESUMBO AMPAI"},{"id":1408012013,"province_id":14,"regency_id":1408,"district_id":1408012,"value":"BATHIN SOBANGA"}]