[{"id":1871071001,"province_id":18,"regency_id":1871,"district_id":1871071,"value":"SUMBER AGUNG"},{"id":1871071002,"province_id":18,"regency_id":1871,"district_id":1871071,"value":"KEDAUNG"},{"id":1871071003,"province_id":18,"regency_id":1871,"district_id":1871071,"value":"PINANG JAYA"},{"id":1871071004,"province_id":18,"regency_id":1871,"district_id":1871071,"value":"BERINGIN RAYA"},{"id":1871071005,"province_id":18,"regency_id":1871,"district_id":1871071,"value":"SUMBER REJO"},{"id":1871071006,"province_id":18,"regency_id":1871,"district_id":1871071,"value":"KEMILING PERMAI"},{"id":1871071008,"province_id":18,"regency_id":1871,"district_id":1871071,"value":"SUMBERREJO SEJAHTERA"},{"id":1871071009,"province_id":18,"regency_id":1871,"district_id":1871071,"value":"BERINGIN JAYA"},{"id":1871071010,"province_id":18,"regency_id":1871,"district_id":1871071,"value":"KEMILING RAYA"}]