[{"id":1601052001,"province_id":16,"regency_id":1601,"district_id":1601052,"value":"BANDAR JAYA"},{"id":1601052002,"province_id":16,"regency_id":1601,"district_id":1601052,"value":"KARANG ENDAH"},{"id":1601052003,"province_id":16,"regency_id":1601,"district_id":1601052,"value":"PAJAR BULAN"},{"id":1601052004,"province_id":16,"regency_id":1601,"district_id":1601052,"value":"PAGAR DEWA"},{"id":1601052005,"province_id":16,"regency_id":1601,"district_id":1601052,"value":"TANJUNG LENGKAYAP"},{"id":1601052006,"province_id":16,"regency_id":1601,"district_id":1601052,"value":"BUMI KAWA"},{"id":1601052007,"province_id":16,"regency_id":1601,"district_id":1601052,"value":"NEGERI RATU"},{"id":1601052008,"province_id":16,"regency_id":1601,"district_id":1601052,"value":"LUBUK DALAM"},{"id":1601052009,"province_id":16,"regency_id":1601,"district_id":1601052,"value":"SEGARA KEMBANG"},{"id":1601052010,"province_id":16,"regency_id":1601,"district_id":1601052,"value":"SUKARAJA"},{"id":1601052011,"province_id":16,"regency_id":1601,"district_id":1601052,"value":"GEDUNG PAKUAN"},{"id":1601052012,"province_id":16,"regency_id":1601,"district_id":1601052,"value":"TUALANG"},{"id":1601052013,"province_id":16,"regency_id":1601,"district_id":1601052,"value":"SUNDAN"},{"id":1601052014,"province_id":16,"regency_id":1601,"district_id":1601052,"value":"TIHANG"},{"id":1601052015,"province_id":16,"regency_id":1601,"district_id":1601052,"value":"LUBUK HARA"},{"id":1601052016,"province_id":16,"regency_id":1601,"district_id":1601052,"value":"NEGERI AGUNG"},{"id":1601052017,"province_id":16,"regency_id":1601,"district_id":1601052,"value":"WAY HELING"},{"id":1601052018,"province_id":16,"regency_id":1601,"district_id":1601052,"value":"BUNGA TANJUNG"},{"id":1601052019,"province_id":16,"regency_id":1601,"district_id":1601052,"value":"UMPAM"},{"id":1601052020,"province_id":16,"regency_id":1601,"district_id":1601052,"value":"TANJUNG AGUNG"},{"id":1601052021,"province_id":16,"regency_id":1601,"district_id":1601052,"value":"SIMPANG EMPAT"},{"id":1601052022,"province_id":16,"regency_id":1601,"district_id":1601052,"value":"FAJAR JAYA"}]