[{"id":1807052001,"province_id":18,"regency_id":1807,"district_id":1807052,"value":"TANJUNG DALOM"},{"id":1807052002,"province_id":18,"regency_id":1807,"district_id":1807052,"value":"KARANGAN"},{"id":1807052003,"province_id":18,"regency_id":1807,"district_id":1807052,"value":"BUMI AGUNG"},{"id":1807052004,"province_id":18,"regency_id":1807,"district_id":1807052,"value":"MULYO HARJO"},{"id":1807052005,"province_id":18,"regency_id":1807,"district_id":1807052,"value":"WONOHARJO"},{"id":1807052006,"province_id":18,"regency_id":1807,"district_id":1807052,"value":"PISANG BARU"},{"id":1807052007,"province_id":18,"regency_id":1807,"district_id":1807052,"value":"SRINUMPI"},{"id":1807052008,"province_id":18,"regency_id":1807,"district_id":1807052,"value":"PISANG INDAH"},{"id":1807052009,"province_id":18,"regency_id":1807,"district_id":1807052,"value":"SUKA MAJU"},{"id":1807052010,"province_id":18,"regency_id":1807,"district_id":1807052,"value":"BUMI SAY AGUNG"}]