[{"id":8108081001,"province_id":81,"regency_id":8108,"district_id":8108081,"value":"BABYOTANG"},{"id":8108081002,"province_id":81,"regency_id":8108,"district_id":8108081,"value":"IBLATMUNTAH"},{"id":8108081003,"province_id":81,"regency_id":8108,"district_id":8108081,"value":"LAWAWANG"},{"id":8108081004,"province_id":81,"regency_id":8108,"district_id":8108081,"value":"TELALORA/LETODA"},{"id":8108081005,"province_id":81,"regency_id":8108,"district_id":8108081,"value":"ILBUTUNG"},{"id":8108081006,"province_id":81,"regency_id":8108,"district_id":8108081,"value":"NURA"},{"id":8108081007,"province_id":81,"regency_id":8108,"district_id":8108081,"value":"LATALOLA BESAR"},{"id":8108081008,"province_id":81,"regency_id":8108,"district_id":8108081,"value":"MARSELA"},{"id":8108081009,"province_id":81,"regency_id":8108,"district_id":8108081,"value":"SERILI"},{"id":8108081010,"province_id":81,"regency_id":8108,"district_id":8108081,"value":"LATALOLA KECIL"},{"id":8108081011,"province_id":81,"regency_id":8108,"district_id":8108081,"value":"BULULORA"}]