[{"id":1171010,"province_id":11,"regency_id":1171,"value":"MEURAXA"},{"id":1171011,"province_id":11,"regency_id":1171,"value":"JAYA BARU"},{"id":1171012,"province_id":11,"regency_id":1171,"value":"BANDA RAYA"},{"id":1171020,"province_id":11,"regency_id":1171,"value":"BAITURRAHMAN"},{"id":1171021,"province_id":11,"regency_id":1171,"value":"LUENG BATA"},{"id":1171030,"province_id":11,"regency_id":1171,"value":"KUTA ALAM"},{"id":1171031,"province_id":11,"regency_id":1171,"value":"KUTA RAJA"},{"id":1171040,"province_id":11,"regency_id":1171,"value":"SYIAH KUALA"},{"id":1171041,"province_id":11,"regency_id":1171,"value":"ULEE KARENG"}]