[{"id":3603190001,"province_id":36,"regency_id":3603,"district_id":3603190,"value":"BUNISARI"},{"id":3603190002,"province_id":36,"regency_id":3603,"district_id":3603190,"value":"RAWA BONI"},{"id":3603190003,"province_id":36,"regency_id":3603,"district_id":3603190,"value":"KIARA PAYUNG"},{"id":3603190004,"province_id":36,"regency_id":3603,"district_id":3603190,"value":"GAGA"},{"id":3603190005,"province_id":36,"regency_id":3603,"district_id":3603190,"value":"LAKSANA"},{"id":3603190006,"province_id":36,"regency_id":3603,"district_id":3603190,"value":"BUARAN BAMBU"},{"id":3603190007,"province_id":36,"regency_id":3603,"district_id":3603190,"value":"PAKU HAJI"},{"id":3603190008,"province_id":36,"regency_id":3603,"district_id":3603190,"value":"PAKU ALAM"},{"id":3603190009,"province_id":36,"regency_id":3603,"district_id":3603190,"value":"BUARAN MANGGA"},{"id":3603190010,"province_id":36,"regency_id":3603,"district_id":3603190,"value":"SURYA BAHARI"},{"id":3603190011,"province_id":36,"regency_id":3603,"district_id":3603190,"value":"SUKAWALI"},{"id":3603190012,"province_id":36,"regency_id":3603,"district_id":3603190,"value":"KRAMAT"},{"id":3603190013,"province_id":36,"regency_id":3603,"district_id":3603190,"value":"KALIBARU"},{"id":3603190014,"province_id":36,"regency_id":3603,"district_id":3603190,"value":"KOHOD"}]