[{"id":3273010,"province_id":32,"regency_id":3273,"value":"BANDUNG KULON"},{"id":3273020,"province_id":32,"regency_id":3273,"value":"BABAKAN CIPARAY"},{"id":3273030,"province_id":32,"regency_id":3273,"value":"BOJONGLOA KALER"},{"id":3273040,"province_id":32,"regency_id":3273,"value":"BOJONGLOA KIDUL"},{"id":3273050,"province_id":32,"regency_id":3273,"value":"ASTANAANYAR"},{"id":3273060,"province_id":32,"regency_id":3273,"value":"REGOL"},{"id":3273070,"province_id":32,"regency_id":3273,"value":"LENGKONG"},{"id":3273080,"province_id":32,"regency_id":3273,"value":"BANDUNG KIDUL"},{"id":3273090,"province_id":32,"regency_id":3273,"value":"BUAHBATU"},{"id":3273100,"province_id":32,"regency_id":3273,"value":"RANCASARI"},{"id":3273101,"province_id":32,"regency_id":3273,"value":"GEDEBAGE"},{"id":3273110,"province_id":32,"regency_id":3273,"value":"CIBIRU"},{"id":3273111,"province_id":32,"regency_id":3273,"value":"PANYILEUKAN"},{"id":3273120,"province_id":32,"regency_id":3273,"value":"UJUNG BERUNG"},{"id":3273121,"province_id":32,"regency_id":3273,"value":"CINAMBO"},{"id":3273130,"province_id":32,"regency_id":3273,"value":"ARCAMANIK"},{"id":3273141,"province_id":32,"regency_id":3273,"value":"ANTAPANI"},{"id":3273142,"province_id":32,"regency_id":3273,"value":"MANDALAJATI"},{"id":3273150,"province_id":32,"regency_id":3273,"value":"KIARACONDONG"},{"id":3273160,"province_id":32,"regency_id":3273,"value":"BATUNUNGGAL"},{"id":3273170,"province_id":32,"regency_id":3273,"value":"SUMUR BANDUNG"},{"id":3273180,"province_id":32,"regency_id":3273,"value":"ANDIR"},{"id":3273190,"province_id":32,"regency_id":3273,"value":"CICENDO"},{"id":3273200,"province_id":32,"regency_id":3273,"value":"BANDUNG WETAN"},{"id":3273210,"province_id":32,"regency_id":3273,"value":"CIBEUNYING KIDUL"},{"id":3273220,"province_id":32,"regency_id":3273,"value":"CIBEUNYING KALER"},{"id":3273230,"province_id":32,"regency_id":3273,"value":"COBLONG"},{"id":3273240,"province_id":32,"regency_id":3273,"value":"SUKAJADI"},{"id":3273250,"province_id":32,"regency_id":3273,"value":"SUKASARI"},{"id":3273260,"province_id":32,"regency_id":3273,"value":"CIDADAP"}]