[{"id":8204051001,"province_id":82,"regency_id":8204,"district_id":8204051,"value":"KAKUPANG"},{"id":8204051002,"province_id":82,"regency_id":8204,"district_id":8204051,"value":"MARIKAPAL"},{"id":8204051003,"province_id":82,"regency_id":8204,"district_id":8204051,"value":"BISORI"},{"id":8204051004,"province_id":82,"regency_id":8204,"district_id":8204051,"value":"DOKO"},{"id":8204051005,"province_id":82,"regency_id":8204,"district_id":8204051,"value":"PALAMEA"},{"id":8204051006,"province_id":82,"regency_id":8204,"district_id":8204051,"value":"ARUMAMANG"},{"id":8204051007,"province_id":82,"regency_id":8204,"district_id":8204051,"value":"LATA LATA"},{"id":8204051008,"province_id":82,"regency_id":8204,"district_id":8204051,"value":"SIDANGA"},{"id":8204051009,"province_id":82,"regency_id":8204,"district_id":8204051,"value":"SENGGA BARU"},{"id":8204051010,"province_id":82,"regency_id":8204,"district_id":8204051,"value":"IMBU IMBU"}]