[{"id":1610030001,"province_id":16,"regency_id":1610,"district_id":1610030,"value":"KELAMPAIAN"},{"id":1610030002,"province_id":16,"regency_id":1610,"district_id":1610030,"value":"SUKA NANTI"},{"id":1610030003,"province_id":16,"regency_id":1610,"district_id":1610030,"value":"RANTAU ALAI"},{"id":1610030004,"province_id":16,"regency_id":1610,"district_id":1610030,"value":"KERTABAYANG"},{"id":1610030005,"province_id":16,"regency_id":1610,"district_id":1610030,"value":"SUKA MAJU"},{"id":1610030006,"province_id":16,"regency_id":1610,"district_id":1610030,"value":"SUKAMARGA"},{"id":1610030007,"province_id":16,"regency_id":1610,"district_id":1610030,"value":"SANDING MARGA"},{"id":1610030011,"province_id":16,"regency_id":1610,"district_id":1610030,"value":"TANJUNG MAS"},{"id":1610030012,"province_id":16,"regency_id":1610,"district_id":1610030,"value":"LEBUNG BANDUNG"},{"id":1610030013,"province_id":16,"regency_id":1610,"district_id":1610030,"value":"TALANG SARI"},{"id":1610030019,"province_id":16,"regency_id":1610,"district_id":1610030,"value":"SIRAH PULAU KILIP"},{"id":1610030020,"province_id":16,"regency_id":1610,"district_id":1610030,"value":"MEKAR SARI"},{"id":1610030021,"province_id":16,"regency_id":1610,"district_id":1610030,"value":"SUKANANTI  BARU"}]