[{"id":1707053001,"province_id":17,"regency_id":1707,"district_id":1707053,"value":"KETENONG SATU"},{"id":1707053002,"province_id":17,"regency_id":1707,"district_id":1707053,"value":"KETENONG DUA"},{"id":1707053003,"province_id":17,"regency_id":1707,"district_id":1707053,"value":"KETENONG JAYA"},{"id":1707053004,"province_id":17,"regency_id":1707,"district_id":1707053,"value":"TAMBANG SAWEAK"},{"id":1707053005,"province_id":17,"regency_id":1707,"district_id":1707053,"value":"AIR KOPRAS"},{"id":1707053006,"province_id":17,"regency_id":1707,"district_id":1707053,"value":"BIOA PUTIAK"},{"id":1707053007,"province_id":17,"regency_id":1707,"district_id":1707053,"value":"SEBELET"},{"id":1707053008,"province_id":17,"regency_id":1707,"district_id":1707053,"value":"SUNGAI LISAI"}]