[{"id":6402050010,"province_id":64,"regency_id":6402,"district_id":6402050,"value":"MUARA BEGAI"},{"id":6402050011,"province_id":64,"regency_id":6402,"district_id":6402050,"value":"LOTAQ"},{"id":6402050012,"province_id":64,"regency_id":6402,"district_id":6402050,"value":"PAYANG"},{"id":6402050013,"province_id":64,"regency_id":6402,"district_id":6402050,"value":"CEMPEDAS"},{"id":6402050014,"province_id":64,"regency_id":6402,"district_id":6402050,"value":"DINGIN"},{"id":6402050015,"province_id":64,"regency_id":6402,"district_id":6402050,"value":"MUARA LAWA"},{"id":6402050016,"province_id":64,"regency_id":6402,"district_id":6402050,"value":"LAMBING"},{"id":6402050017,"province_id":64,"regency_id":6402,"district_id":6402050,"value":"BENGGERIS"}]