[{"id":6311040001,"province_id":63,"regency_id":6311,"district_id":6311040,"value":"LAMIDA"},{"id":6311040002,"province_id":63,"regency_id":6311,"district_id":6311040,"value":"LOK BATUNG"},{"id":6311040003,"province_id":63,"regency_id":6311,"district_id":6311040,"value":"BABAYAU"},{"id":6311040004,"province_id":63,"regency_id":6311,"district_id":6311040,"value":"PARAN"},{"id":6311040005,"province_id":63,"regency_id":6311,"district_id":6311040,"value":"MANGKAYAHU"},{"id":6311040006,"province_id":63,"regency_id":6311,"district_id":6311040,"value":"BALANG"},{"id":6311040007,"province_id":63,"regency_id":6311,"district_id":6311040,"value":"MURUNG ILUNG"},{"id":6311040008,"province_id":63,"regency_id":6311,"district_id":6311040,"value":"HUJAN MAS"},{"id":6311040009,"province_id":63,"regency_id":6311,"district_id":6311040,"value":"KALAHIANG"},{"id":6311040010,"province_id":63,"regency_id":6311,"district_id":6311040,"value":"LAYAP"},{"id":6311040013,"province_id":63,"regency_id":6311,"district_id":6311040,"value":"PARINGIN KOTA"},{"id":6311040014,"province_id":63,"regency_id":6311,"district_id":6311040,"value":"PARINGIN TIMUR"},{"id":6311040016,"province_id":63,"regency_id":6311,"district_id":6311040,"value":"BALIDA"},{"id":6311040018,"province_id":63,"regency_id":6311,"district_id":6311040,"value":"LASUNG BATU"},{"id":6311040019,"province_id":63,"regency_id":6311,"district_id":6311040,"value":"SUNGAI KATAPI"},{"id":6311040020,"province_id":63,"regency_id":6311,"district_id":6311040,"value":"DAHAI"}]