[{"id":3329120001,"province_id":33,"regency_id":3329,"district_id":3329120,"value":"KRADENAN"},{"id":3329120002,"province_id":33,"regency_id":3329,"district_id":3329120,"value":"SINDANGJAYA"},{"id":3329120004,"province_id":33,"regency_id":3329,"district_id":3329120,"value":"KUBANGPARI"},{"id":3329120005,"province_id":33,"regency_id":3329,"district_id":3329120,"value":"CIKANDANG"},{"id":3329120006,"province_id":33,"regency_id":3329,"district_id":3329120,"value":"CIGEDOG"},{"id":3329120007,"province_id":33,"regency_id":3329,"district_id":3329120,"value":"CIAMPEL"},{"id":3329120008,"province_id":33,"regency_id":3329,"district_id":3329120,"value":"JAGAPURA"},{"id":3329120009,"province_id":33,"regency_id":3329,"district_id":3329120,"value":"KERSANA"},{"id":3329120011,"province_id":33,"regency_id":3329,"district_id":3329120,"value":"KRAMATSAMPANG"},{"id":3329120012,"province_id":33,"regency_id":3329,"district_id":3329120,"value":"LIMBANGAN"},{"id":3329120013,"province_id":33,"regency_id":3329,"district_id":3329120,"value":"SUTAMAJA"}]