[{"id":7471031001,"province_id":74,"regency_id":7471,"district_id":7471031,"value":"KEMARAYA"},{"id":7471031002,"province_id":74,"regency_id":7471,"district_id":7471031,"value":"WATU-WATU"},{"id":7471031003,"province_id":74,"regency_id":7471,"district_id":7471031,"value":"TIPULU"},{"id":7471031004,"province_id":74,"regency_id":7471,"district_id":7471031,"value":"PUNGGALOBA"},{"id":7471031005,"province_id":74,"regency_id":7471,"district_id":7471031,"value":"BENU-BENUA"},{"id":7471031006,"province_id":74,"regency_id":7471,"district_id":7471031,"value":"SODOHOA"},{"id":7471031007,"province_id":74,"regency_id":7471,"district_id":7471031,"value":"SANUA"},{"id":7471031008,"province_id":74,"regency_id":7471,"district_id":7471031,"value":"DAPU-DAPURA"},{"id":7471031009,"province_id":74,"regency_id":7471,"district_id":7471031,"value":"LAHUNDAPE"}]