[{"id":3206030001,"province_id":32,"regency_id":3206,"district_id":3206030,"value":"MANDALAJAYA"},{"id":3206030002,"province_id":32,"regency_id":3206,"district_id":3206030,"value":"CIKALONG"},{"id":3206030003,"province_id":32,"regency_id":3206,"district_id":3206030,"value":"CIKANCRA"},{"id":3206030004,"province_id":32,"regency_id":3206,"district_id":3206030,"value":"TONJONGSARI"},{"id":3206030005,"province_id":32,"regency_id":3206,"district_id":3206030,"value":"SINGKIR"},{"id":3206030006,"province_id":32,"regency_id":3206,"district_id":3206030,"value":"PANYIARAN"},{"id":3206030007,"province_id":32,"regency_id":3206,"district_id":3206030,"value":"CIBEBER"},{"id":3206030008,"province_id":32,"regency_id":3206,"district_id":3206030,"value":"CIDADALI"},{"id":3206030009,"province_id":32,"regency_id":3206,"district_id":3206030,"value":"KUBANGSARI"},{"id":3206030010,"province_id":32,"regency_id":3206,"district_id":3206030,"value":"CIKADU"},{"id":3206030011,"province_id":32,"regency_id":3206,"district_id":3206030,"value":"SINDANGJAYA"},{"id":3206030012,"province_id":32,"regency_id":3206,"district_id":3206030,"value":"KALAPAGENEP"},{"id":3206030013,"province_id":32,"regency_id":3206,"district_id":3206030,"value":"CIMANUK"}]