[{"id":3202111001,"province_id":32,"regency_id":3202,"district_id":3202111,"value":"CIHAUR"},{"id":3202111002,"province_id":32,"regency_id":3202,"district_id":3202111,"value":"KERTAJAYA"},{"id":3202111003,"province_id":32,"regency_id":3202,"district_id":3202111,"value":"LOJI"},{"id":3202111004,"province_id":32,"regency_id":3202,"district_id":3202111,"value":"CIDADAP"},{"id":3202111005,"province_id":32,"regency_id":3202,"district_id":3202111,"value":"CIBUNTU"},{"id":3202111006,"province_id":32,"regency_id":3202,"district_id":3202111,"value":"MEKARASIH"},{"id":3202111007,"province_id":32,"regency_id":3202,"district_id":3202111,"value":"SANGRAWAYANG"}]