[{"id":3520070001,"province_id":35,"regency_id":3520,"district_id":3520070,"value":"NGANCAR"},{"id":3520070003,"province_id":35,"regency_id":3520,"district_id":3520070,"value":"PUNTUKDORO"},{"id":3520070005,"province_id":35,"regency_id":3520,"district_id":3520070,"value":"BOGOARUM"},{"id":3520070006,"province_id":35,"regency_id":3520,"district_id":3520070,"value":"RANDUGEDE"},{"id":3520070007,"province_id":35,"regency_id":3520,"district_id":3520070,"value":"SUMBERAGUNG"},{"id":3520070008,"province_id":35,"regency_id":3520,"district_id":3520070,"value":"NITIKAN"},{"id":3520070009,"province_id":35,"regency_id":3520,"district_id":3520070,"value":"SIDOMUKTI"},{"id":3520070010,"province_id":35,"regency_id":3520,"district_id":3520070,"value":"BULUHARJO"},{"id":3520070011,"province_id":35,"regency_id":3520,"district_id":3520070,"value":"PLAOSAN"},{"id":3520070012,"province_id":35,"regency_id":3520,"district_id":3520070,"value":"DADI"},{"id":3520070013,"province_id":35,"regency_id":3520,"district_id":3520070,"value":"SARANGAN"},{"id":3520070014,"province_id":35,"regency_id":3520,"district_id":3520070,"value":"PACALAN"},{"id":3520070015,"province_id":35,"regency_id":3520,"district_id":3520070,"value":"SENDANGAGUNG"}]