[{"id":7305051001,"province_id":73,"regency_id":7305,"district_id":7305051,"value":"BONTOLOE"},{"id":7305051002,"province_id":73,"regency_id":7305,"district_id":7305051,"value":"KALENNA BONTONGAPE"},{"id":7305051003,"province_id":73,"regency_id":7305,"district_id":7305051,"value":"BONTOMANGAPE"},{"id":7305051004,"province_id":73,"regency_id":7305,"district_id":7305051,"value":"PARAMBAMBE"},{"id":7305051005,"province_id":73,"regency_id":7305,"district_id":7305051,"value":"PATTINOANG"},{"id":7305051006,"province_id":73,"regency_id":7305,"district_id":7305051,"value":"BODDIA"},{"id":7305051007,"province_id":73,"regency_id":7305,"district_id":7305051,"value":"PARANGMATA"},{"id":7305051008,"province_id":73,"regency_id":7305,"district_id":7305051,"value":"GALESONG KOTA"},{"id":7305051009,"province_id":73,"regency_id":7305,"district_id":7305051,"value":"GALESONG BARU"},{"id":7305051010,"province_id":73,"regency_id":7305,"district_id":7305051,"value":"PALALAKKANG"},{"id":7305051011,"province_id":73,"regency_id":7305,"district_id":7305051,"value":"PARASANGANG BERU"},{"id":7305051012,"province_id":73,"regency_id":7305,"district_id":7305051,"value":"KALUKUANG"},{"id":7305051013,"province_id":73,"regency_id":7305,"district_id":7305051,"value":"MAPPAKALOMPO"},{"id":7305051014,"province_id":73,"regency_id":7305,"district_id":7305051,"value":"CAMPAGAYA"}]