[{"id":6110030001,"province_id":61,"regency_id":6110,"district_id":6110030,"value":"MADYA RAYA"},{"id":6110030002,"province_id":61,"regency_id":6110,"district_id":6110030,"value":"LANDAU SADAK"},{"id":6110030003,"province_id":61,"regency_id":6110,"district_id":6110030,"value":"PEKAWAI"},{"id":6110030004,"province_id":61,"regency_id":6110,"district_id":6110030,"value":"MEKAR PELITA"},{"id":6110030005,"province_id":61,"regency_id":6110,"district_id":6110030,"value":"NANGA SAYAN"},{"id":6110030006,"province_id":61,"regency_id":6110,"district_id":6110030,"value":"KERANGAN PURUN"},{"id":6110030007,"province_id":61,"regency_id":6110,"district_id":6110030,"value":"BORA"},{"id":6110030008,"province_id":61,"regency_id":6110,"district_id":6110030,"value":"NANGA KOMPI"},{"id":6110030009,"province_id":61,"regency_id":6110,"district_id":6110030,"value":"NANGA MANCUR"},{"id":6110030010,"province_id":61,"regency_id":6110,"district_id":6110030,"value":"TUMBAK RAYA"},{"id":6110030011,"province_id":61,"regency_id":6110,"district_id":6110030,"value":"NANGA RAKU"},{"id":6110030012,"province_id":61,"regency_id":6110,"district_id":6110030,"value":"META BERSATU"},{"id":6110030013,"province_id":61,"regency_id":6110,"district_id":6110030,"value":"NANGA KASAI"},{"id":6110030014,"province_id":61,"regency_id":6110,"district_id":6110030,"value":"SILING PERMAI"},{"id":6110030015,"province_id":61,"regency_id":6110,"district_id":6110030,"value":"LINGKAR INDAH"},{"id":6110030016,"province_id":61,"regency_id":6110,"district_id":6110030,"value":"SAYAN JAYA"},{"id":6110030017,"province_id":61,"regency_id":6110,"district_id":6110030,"value":"NANGA PAK"},{"id":6110030018,"province_id":61,"regency_id":6110,"district_id":6110030,"value":"BEROBAI PERMAI"}]