[{"id":8272050003,"province_id":82,"regency_id":8272,"district_id":8272050,"value":"SOMAHODE"},{"id":8272050004,"province_id":82,"regency_id":8272,"district_id":8272050,"value":"AKEKOLANO"},{"id":8272050005,"province_id":82,"regency_id":8272,"district_id":8272050,"value":"OBA"},{"id":8272050006,"province_id":82,"regency_id":8272,"district_id":8272050,"value":"SOFIFI"},{"id":8272050007,"province_id":82,"regency_id":8272,"district_id":8272050,"value":"GURAPING"},{"id":8272050008,"province_id":82,"regency_id":8272,"district_id":8272050,"value":"KAIYASA"},{"id":8272050009,"province_id":82,"regency_id":8272,"district_id":8272050,"value":"GAROJOU"},{"id":8272050011,"province_id":82,"regency_id":8272,"district_id":8272050,"value":"AMPERA"},{"id":8272050012,"province_id":82,"regency_id":8272,"district_id":8272050,"value":"BUKIT DURIAN"},{"id":8272050013,"province_id":82,"regency_id":8272,"district_id":8272050,"value":"GALALA"},{"id":8272050014,"province_id":82,"regency_id":8272,"district_id":8272050,"value":"BALBAR"},{"id":8272050015,"province_id":82,"regency_id":8272,"district_id":8272050,"value":"GOSALE"}]