[{"id":1810070001,"province_id":18,"regency_id":1810,"district_id":1810070,"value":"WAYA KRUI"},{"id":1810070002,"province_id":18,"regency_id":1810,"district_id":1810070,"value":"SRI RAHAYU"},{"id":1810070003,"province_id":18,"regency_id":1810,"district_id":1810070,"value":"NUSA WUNGU"},{"id":1810070004,"province_id":18,"regency_id":1810,"district_id":1810070,"value":"SUKAMULYA"},{"id":1810070005,"province_id":18,"regency_id":1810,"district_id":1810070,"value":"BANJAREJO"},{"id":1810070006,"province_id":18,"regency_id":1810,"district_id":1810070,"value":"SRIWUNGU"},{"id":1810070007,"province_id":18,"regency_id":1810,"district_id":1810070,"value":"BANYUWANGI"},{"id":1810070008,"province_id":18,"regency_id":1810,"district_id":1810070,"value":"BANYUMAS"},{"id":1810070009,"province_id":18,"regency_id":1810,"district_id":1810070,"value":"SINAR MULIA"},{"id":1810070010,"province_id":18,"regency_id":1810,"district_id":1810070,"value":"MULYOREJO"},{"id":1810070011,"province_id":18,"regency_id":1810,"district_id":1810070,"value":"BANYU URIP"}]