[{"id":9412010,"province_id":94,"regency_id":9412,"value":"MIMIKA BARAT"},{"id":9412011,"province_id":94,"regency_id":9412,"value":"MIMIKA BARAT JAUH"},{"id":9412012,"province_id":94,"regency_id":9412,"value":"MIMIKA BARAT TENGAH"},{"id":9412013,"province_id":94,"regency_id":9412,"value":"AMAR"},{"id":9412020,"province_id":94,"regency_id":9412,"value":"MIMIKA TIMUR"},{"id":9412021,"province_id":94,"regency_id":9412,"value":"MIMIKA TENGAH"},{"id":9412022,"province_id":94,"regency_id":9412,"value":"MIMIKA TIMUR JAUH"},{"id":9412030,"province_id":94,"regency_id":9412,"value":"MIMIKA BARU"},{"id":9412031,"province_id":94,"regency_id":9412,"value":"KUALA KENCANA"},{"id":9412032,"province_id":94,"regency_id":9412,"value":"TEMBAGAPURA"},{"id":9412033,"province_id":94,"regency_id":9412,"value":"WANIA"},{"id":9412034,"province_id":94,"regency_id":9412,"value":"IWAKA"},{"id":9412035,"province_id":94,"regency_id":9412,"value":"KWAMKI NARAMA"},{"id":9412040,"province_id":94,"regency_id":9412,"value":"AGIMUGA"},{"id":9412041,"province_id":94,"regency_id":9412,"value":"JILA"},{"id":9412042,"province_id":94,"regency_id":9412,"value":"JITA"},{"id":9412043,"province_id":94,"regency_id":9412,"value":"ALAMA"},{"id":9412044,"province_id":94,"regency_id":9412,"value":"HOYA"}]