[{"id":3208080001,"province_id":32,"regency_id":3208,"district_id":3208080,"value":"WALAHARCAGEUR"},{"id":3208080002,"province_id":32,"regency_id":3208,"district_id":3208080,"value":"DUKUHPICUNG"},{"id":3208080003,"province_id":32,"regency_id":3208,"district_id":3208080,"value":"WILANAGARA"},{"id":3208080004,"province_id":32,"regency_id":3208,"district_id":3208080,"value":"SINDANGSARI"},{"id":3208080005,"province_id":32,"regency_id":3208,"district_id":3208080,"value":"CIGEDANG"},{"id":3208080006,"province_id":32,"regency_id":3208,"district_id":3208080,"value":"LURAGUNGTONGGOH"},{"id":3208080007,"province_id":32,"regency_id":3208,"district_id":3208080,"value":"MARGASARI"},{"id":3208080008,"province_id":32,"regency_id":3208,"district_id":3208080,"value":"CIRAHAYU"},{"id":3208080009,"province_id":32,"regency_id":3208,"district_id":3208080,"value":"SINDANGSUKA"},{"id":3208080010,"province_id":32,"regency_id":3208,"district_id":3208080,"value":"CIKANDANG"},{"id":3208080011,"province_id":32,"regency_id":3208,"district_id":3208080,"value":"PANYOSOGAN"},{"id":3208080012,"province_id":32,"regency_id":3208,"district_id":3208080,"value":"GUNUNGKARUNG"},{"id":3208080013,"province_id":32,"regency_id":3208,"district_id":3208080,"value":"DUKUHMAJA"},{"id":3208080014,"province_id":32,"regency_id":3208,"district_id":3208080,"value":"LURAGUNGLANDEUH"},{"id":3208080015,"province_id":32,"regency_id":3208,"district_id":3208080,"value":"CIKADUWETAN"},{"id":3208080016,"province_id":32,"regency_id":3208,"district_id":3208080,"value":"BENDA"}]