[{"id":3215170001,"province_id":32,"regency_id":3215,"district_id":3215170,"value":"SUKASARI"},{"id":3215170002,"province_id":32,"regency_id":3215,"district_id":3215170,"value":"KERTARAHAYU"},{"id":3215170003,"province_id":32,"regency_id":3215,"district_id":3215170,"value":"CIBUAYA"},{"id":3215170004,"province_id":32,"regency_id":3215,"district_id":3215170,"value":"PEJATEN"},{"id":3215170006,"province_id":32,"regency_id":3215,"district_id":3215170,"value":"KALIDUNGJAYA"},{"id":3215170007,"province_id":32,"regency_id":3215,"district_id":3215170,"value":"KEDUNGJAYA"},{"id":3215170008,"province_id":32,"regency_id":3215,"district_id":3215170,"value":"JAYAMULYA"},{"id":3215170009,"province_id":32,"regency_id":3215,"district_id":3215170,"value":"GEBANGJAYA"},{"id":3215170010,"province_id":32,"regency_id":3215,"district_id":3215170,"value":"CEMARAJAYA"},{"id":3215170011,"province_id":32,"regency_id":3215,"district_id":3215170,"value":"SEDARI"}]